{
  "v": 1,
  "types": {
    "0": "zwrotka",
    "1": "refren",
    "2": "wstęp",
    "3": "zakończenie",
    "4": "fragment"
  },
  "songs": {
    "Aklamacja-przed-Ewangelia-w-Wielkim-Poscie-1": [
      [
        0,
        1,
        2,
        1
      ],
      [
        1,
        3,
        5,
        4
      ],
      [
        0,
        6,
        7,
        1
      ]
    ],
    "Aklamacja-przed-Ewangelia-w-Wielkim-Poscie-2": [
      [
        2,
        1,
        2,
        1
      ],
      [
        3,
        3,
        5,
        4
      ],
      [
        2,
        6,
        7,
        1
      ]
    ],
    "Aklamacja-przed-Ewangelia-w-Wielkim-Poscie-3": [
      [
        4,
        1,
        2,
        1
      ],
      [
        5,
        3,
        5,
        4
      ],
      [
        4,
        6,
        7,
        1
      ]
    ],
    "Alleluja-Paschalne": [
      [
        6,
        1,
        6,
        0
      ],
      [
        7,
        7,
        12,
        0
      ],
      [
        8,
        13,
        18,
        0
      ]
    ],
    "Alleluja-aklamacji-przed-Ewangelia-1": [
      [
        9,
        1,
        1,
        1
      ],
      [
        10,
        2,
        4,
        4
      ],
      [
        9,
        5,
        5,
        1
      ]
    ],
    "Alleluja-aklamacji-przed-Ewangelia-2": [
      [
        11,
        1,
        2,
        1
      ],
      [
        12,
        3,
        4,
        4
      ],
      [
        11,
        5,
        6,
        1
      ]
    ],
    "Alleluja-aklamacji-przed-Ewangelia-3": [
      [
        13,
        1,
        2,
        1
      ],
      [
        14,
        3,
        5,
        4
      ],
      [
        15,
        6,
        6,
        1
      ]
    ],
    "Anafora-Liturgii-pokutnej": [
      [
        16,
        1,
        6,
        2
      ],
      [
        17,
        7,
        9,
        4
      ],
      [
        18,
        11,
        17,
        4
      ],
      [
        19,
        18,
        20,
        4
      ]
    ],
    "Baranku-Bozy": [
      [
        20,
        1,
        4,
        4
      ],
      [
        20,
        5,
        8,
        4
      ],
      [
        21,
        9,
        13,
        4
      ],
      [
        22,
        14,
        17,
        4
      ],
      [
        22,
        18,
        21,
        4
      ],
      [
        23,
        22,
        25,
        4
      ]
    ],
    "Blogoslawienie-wody-zrodla-chrzcielnego": [
      [
        24,
        1,
        8,
        4
      ],
      [
        25,
        9,
        14,
        4
      ],
      [
        26,
        15,
        18,
        4
      ],
      [
        27,
        19,
        19,
        3
      ]
    ],
    "Blogoslawienstwo-nowo-poslubionych": [
      [
        28,
        1,
        5,
        4
      ],
      [
        29,
        6,
        7,
        4
      ],
      [
        30,
        8,
        10,
        4
      ],
      [
        31,
        11,
        14,
        4
      ],
      [
        32,
        15,
        19,
        4
      ],
      [
        33,
        20,
        25,
        4
      ],
      [
        34,
        26,
        27,
        4
      ],
      [
        35,
        28,
        28,
        3
      ]
    ],
    "Chwala-Bogu-na-wysokosci": [
      [
        36,
        1,
        4,
        4
      ],
      [
        37,
        5,
        8,
        4
      ],
      [
        38,
        9,
        13,
        4
      ],
      [
        39,
        14,
        16,
        4
      ],
      [
        40,
        17,
        19,
        3
      ]
    ],
    "Credo": [
      [
        41,
        1,
        2,
        4
      ],
      [
        42,
        3,
        6,
        4
      ],
      [
        43,
        7,
        9,
        4
      ],
      [
        44,
        10,
        13,
        4
      ],
      [
        45,
        14,
        19,
        4
      ],
      [
        46,
        20,
        20,
        3
      ]
    ],
    "Litania-do-wszystkich-swietych": [
      [
        47,
        1,
        3,
        4
      ],
      [
        48,
        4,
        5,
        4
      ],
      [
        49,
        6,
        31,
        4
      ],
      [
        50,
        36,
        36,
        4
      ],
      [
        51,
        37,
        38,
        4
      ],
      [
        52,
        39,
        44,
        4
      ],
      [
        53,
        45,
        46,
        4
      ],
      [
        54,
        48,
        48,
        4
      ],
      [
        55,
        50,
        50,
        4
      ],
      [
        56,
        51,
        52,
        4
      ],
      [
        57,
        53,
        56,
        3
      ]
    ],
    "Litania-pokutna-I": [
      [
        58,
        1,
        4,
        0
      ],
      [
        59,
        5,
        8,
        0
      ],
      [
        60,
        9,
        12,
        0
      ],
      [
        61,
        13,
        16,
        0
      ],
      [
        62,
        17,
        20,
        0
      ],
      [
        63,
        21,
        24,
        0
      ],
      [
        64,
        25,
        28,
        0
      ],
      [
        65,
        29,
        32,
        0
      ],
      [
        66,
        33,
        36,
        0
      ],
      [
        67,
        37,
        39,
        0
      ]
    ],
    "Litania-pokutna-II": [
      [
        68,
        1,
        3,
        0
      ],
      [
        69,
        4,
        24,
        4
      ],
      [
        70,
        25,
        31,
        4
      ],
      [
        71,
        32,
        55,
        4
      ],
      [
        72,
        56,
        56,
        3
      ]
    ],
    "Melodia-Ewangelii-spiewanej": [
      [
        73,
        1,
        4,
        2
      ],
      [
        74,
        5,
        10,
        4
      ],
      [
        75,
        11,
        12,
        3
      ]
    ],
    "Melodia-Modlitwy-powszechnej": [
      [
        76,
        1,
        8,
        4
      ],
      [
        77,
        9,
        14,
        4
      ],
      [
        78,
        15,
        19,
        4
      ],
      [
        79,
        20,
        24,
        4
      ]
    ],
    "Melodia-Psalmu-responsoryjnego-1": [
      [
        80,
        1,
        3,
        1
      ],
      [
        81,
        4,
        8,
        0
      ],
      [
        80,
        9,
        10,
        1
      ]
    ],
    "Melodia-Psalmu-responsoryjnego-2": [
      [
        82,
        1,
        2,
        1
      ],
      [
        83,
        3,
        7,
        0
      ],
      [
        82,
        8,
        9,
        1
      ],
      [
        84,
        10,
        14,
        0
      ],
      [
        82,
        15,
        15,
        1
      ]
    ],
    "Melodie-Psalmodii-Jutrzni": [
      [
        85,
        3,
        7,
        4
      ],
      [
        86,
        10,
        14,
        4
      ],
      [
        87,
        17,
        21,
        4
      ],
      [
        88,
        24,
        28,
        4
      ],
      [
        89,
        31,
        39,
        4
      ],
      [
        90,
        42,
        46,
        4
      ],
      [
        91,
        50,
        54,
        4
      ],
      [
        92,
        57,
        64,
        4
      ],
      [
        93,
        67,
        71,
        4
      ],
      [
        94,
        74,
        79,
        4
      ],
      [
        94,
        82,
        86,
        4
      ]
    ],
    "Modlitwa-eucharystyczna-II-1-Doksologia-koncowa-1": [
      [
        95,
        1,
        8,
        4
      ],
      [
        96,
        9,
        13,
        4
      ]
    ],
    "Modlitwa-eucharystyczna-II-1-Doksologia-koncowa-2": [
      [
        97,
        1,
        6,
        4
      ]
    ],
    "Modlitwa-eucharystyczna-II-1-Konsekracja-i-Aklamacja": [
      [
        98,
        2,
        3,
        4
      ],
      [
        99,
        5,
        7,
        4
      ],
      [
        100,
        9,
        22,
        4
      ],
      [
        101,
        24,
        28,
        4
      ]
    ],
    "Modlitwa-eucharystyczna-II-1-Prefacja-Adwentowa": [
      [
        102,
        1,
        7,
        0
      ],
      [
        103,
        8,
        11,
        4
      ],
      [
        104,
        12,
        17,
        0
      ],
      [
        105,
        18,
        20,
        4
      ]
    ],
    "Modlitwa-eucharystyczna-II-1-Prefacja-Paschalna": [
      [
        106,
        1,
        6,
        0
      ],
      [
        107,
        7,
        10,
        4
      ],
      [
        108,
        12,
        17,
        0
      ],
      [
        109,
        18,
        23,
        4
      ]
    ],
    "Modlitwa-eucharystyczna-II-1-Prefacja": [
      [
        110,
        1,
        6,
        0
      ],
      [
        111,
        7,
        10,
        4
      ],
      [
        112,
        11,
        14,
        0
      ],
      [
        113,
        16,
        18,
        0
      ],
      [
        114,
        19,
        21,
        4
      ]
    ],
    "Modlitwa-eucharystyczna-II-1-Slowa-po-Konsekracji": [
      [
        115,
        2,
        4,
        0
      ],
      [
        116,
        6,
        7,
        0
      ],
      [
        117,
        9,
        15,
        4
      ],
      [
        118,
        17,
        24,
        0
      ]
    ],
    "Modlitwa-eucharystyczna-II-2-1987-Konsekracja-i-Aklamacja": [
      [
        119,
        2,
        2,
        4
      ],
      [
        120,
        4,
        5,
        4
      ],
      [
        121,
        7,
        19,
        0
      ],
      [
        122,
        21,
        25,
        1
      ]
    ],
    "Modlitwa-eucharystyczna-II-2-1987-Prefacja-na-Okres-Zwykly": [
      [
        123,
        1,
        6,
        0
      ],
      [
        124,
        7,
        10,
        4
      ],
      [
        125,
        11,
        14,
        0
      ],
      [
        126,
        15,
        18,
        0
      ],
      [
        127,
        20,
        21,
        4
      ],
      [
        128,
        23,
        25,
        4
      ]
    ],
    "Modlitwa-eucharystyczna-IV-Anamneza-i-Ofiarowanie": [
      [
        129,
        1,
        9,
        0
      ],
      [
        130,
        10,
        15,
        0
      ],
      [
        131,
        16,
        17,
        1
      ]
    ],
    "Modlitwa-eucharystyczna-IV-Konsekracja": [
      [
        132,
        2,
        5,
        4
      ],
      [
        133,
        7,
        19,
        0
      ],
      [
        134,
        21,
        24,
        1
      ]
    ],
    "Modlitwa-eucharystyczna-IV-Modlitwy-i-Doksologia": [
      [
        135,
        2,
        10,
        4
      ],
      [
        136,
        12,
        19,
        4
      ],
      [
        137,
        21,
        26,
        4
      ]
    ],
    "Modlitwa-eucharystyczna-IV-Prefacja": [
      [
        138,
        1,
        7,
        2
      ],
      [
        139,
        8,
        22,
        4
      ]
    ],
    "Modlitwa-eucharystyczna-IV-Przejscie": [
      [
        140,
        1,
        7,
        4
      ],
      [
        141,
        8,
        14,
        4
      ],
      [
        142,
        15,
        22,
        4
      ]
    ],
    "Ojcze-nasz": [
      [
        143,
        1,
        4,
        2
      ],
      [
        144,
        5,
        9,
        4
      ],
      [
        145,
        10,
        14,
        4
      ],
      [
        146,
        15,
        15,
        3
      ]
    ],
    "Oredzie-Paschalne": [
      [
        147,
        1,
        9,
        2
      ],
      [
        148,
        10,
        15,
        4
      ],
      [
        149,
        16,
        20,
        4
      ],
      [
        150,
        21,
        25,
        4
      ],
      [
        151,
        26,
        28,
        1
      ],
      [
        152,
        29,
        33,
        4
      ],
      [
        153,
        34,
        36,
        4
      ],
      [
        154,
        37,
        43,
        4
      ],
      [
        151,
        44,
        46,
        1
      ],
      [
        155,
        47,
        58,
        4
      ],
      [
        156,
        59,
        59,
        3
      ]
    ],
    "Rozaniec-spiewany": [
      [
        157,
        4,
        10,
        4
      ],
      [
        158,
        11,
        17,
        4
      ],
      [
        159,
        18,
        21,
        4
      ]
    ],
    "Swiety-1982": [
      [
        160,
        1,
        6,
        4
      ],
      [
        161,
        7,
        9,
        1
      ],
      [
        162,
        10,
        13,
        4
      ],
      [
        161,
        14,
        15,
        1
      ]
    ],
    "Swiety-1988": [
      [
        163,
        1,
        5,
        4
      ],
      [
        164,
        6,
        10,
        4
      ],
      [
        165,
        11,
        14,
        3
      ]
    ],
    "Swiety-Palm": [
      [
        166,
        1,
        7,
        4
      ],
      [
        167,
        8,
        12,
        4
      ],
      [
        168,
        13,
        18,
        1
      ],
      [
        169,
        19,
        23,
        4
      ],
      [
        168,
        24,
        28,
        1
      ]
    ],
    "Swiety-jest-swiety": [
      [
        170,
        1,
        4,
        4
      ],
      [
        171,
        5,
        7,
        4
      ],
      [
        172,
        8,
        10,
        4
      ],
      [
        170,
        11,
        14,
        4
      ],
      [
        173,
        15,
        17,
        4
      ],
      [
        174,
        18,
        22,
        4
      ]
    ],
    "Swiety-rzymskie": [
      [
        175,
        1,
        3,
        4
      ],
      [
        176,
        4,
        8,
        4
      ],
      [
        177,
        9,
        11,
        1
      ],
      [
        177,
        12,
        14,
        1
      ],
      [
        178,
        15,
        19,
        4
      ],
      [
        177,
        20,
        22,
        1
      ],
      [
        177,
        23,
        24,
        1
      ]
    ],
    "Swiety-z-Barakow": [
      [
        179,
        1,
        5,
        4
      ],
      [
        180,
        6,
        10,
        4
      ],
      [
        179,
        11,
        15,
        4
      ],
      [
        181,
        16,
        20,
        4
      ],
      [
        182,
        21,
        25,
        4
      ],
      [
        179,
        26,
        29,
        4
      ]
    ],
    "Te-Deum": [
      [
        183,
        1,
        5,
        4
      ],
      [
        184,
        6,
        11,
        4
      ],
      [
        185,
        12,
        16,
        4
      ],
      [
        186,
        17,
        21,
        4
      ],
      [
        187,
        22,
        26,
        4
      ],
      [
        188,
        27,
        31,
        4
      ],
      [
        189,
        32,
        36,
        4
      ],
      [
        190,
        37,
        41,
        4
      ],
      [
        191,
        42,
        46,
        4
      ],
      [
        192,
        47,
        50,
        4
      ]
    ],
    "Wezwania-i-odpowiedzi-modlitwy-wiernych": [
      [
        193,
        3,
        5,
        4
      ],
      [
        194,
        8,
        10,
        4
      ],
      [
        195,
        13,
        15,
        4
      ],
      [
        196,
        18,
        18,
        4
      ]
    ]
  }
}